prowler_sdk_poc/__init__.py
prowler_sdk_poc/py.typed
prowler_sdk_poc/_jsii/__init__.py
prowler_sdk_poc/_jsii/prowler-sdk-poc@0.0.1.jsii.tgz
prowler_sdk_poc-0.0.1.dist-info/LICENSE
prowler_sdk_poc-0.0.1.dist-info/METADATA
prowler_sdk_poc-0.0.1.dist-info/WHEEL
prowler_sdk_poc-0.0.1.dist-info/top_level.txt
prowler_sdk_poc-0.0.1.dist-info/RECORD
