Metadata-Version: 2.1
Name: prowler-sdk-poc
Version: 0.0.1
Summary: prowler-sdk-poc
Home-page: https://github.com/mmuller88/prowler-sdk-poc
Author: Martin Mueller<damadden88@googlemail.com>
License: Apache-2.0
Project-URL: Source, https://github.com/mmuller88/prowler-sdk-poc
Platform: UNKNOWN
Classifier: Intended Audience :: Developers
Classifier: Operating System :: OS Independent
Classifier: Programming Language :: JavaScript
Classifier: Programming Language :: Python :: 3 :: Only
Classifier: Programming Language :: Python :: 3.6
Classifier: Programming Language :: Python :: 3.7
Classifier: Programming Language :: Python :: 3.8
Classifier: Programming Language :: Python :: 3.9
Classifier: Typing :: Typed
Classifier: Development Status :: 5 - Production/Stable
Classifier: License :: OSI Approved
Requires-Python: >=3.6
License-File: LICENSE
Requires-Dist: jsii (<2.0.0,>=1.40.0)
Requires-Dist: publication (>=0.0.3)
